MANIFEST.in
README.rst
setup.py
pyeventbus/Singleton.py
pyeventbus/__init__.py
pyeventbus/pyeventbus.py
pyeventbus.egg-info/PKG-INFO
pyeventbus.egg-info/SOURCES.txt
pyeventbus.egg-info/dependency_links.txt
pyeventbus.egg-info/not-zip-safe
pyeventbus.egg-info/requires.txt
pyeventbus.egg-info/top_level.txt